{"icon":{"36":"resources/icons/Icon_Android36.png","48":"resources/icons/Icon_Android48.png","72":"resources/icons/Icon~ipad.png"},"platform":"AndroidEmulator","outputPath":"C:\\xampp2\\htdocs\\touch-2.2.1\\Appmobileauf/build/native-package-mobile/VeilleAUF/packager.json","applicationName":"Appmobileauf","applicationId":"com.mycompany.myAppID","versionCode":"1","sdkPath":"C:/axandroid/android-sdk-window/sdk","versionString":"1.0","inputPath":"C:\\xampp2\\htdocs\\touch-2.2.1\\Appmobileauf/build/native/VeilleAUF","certificatePath":"","certificatePassword":"","deviceType":"Universal","androidAPILevel":"8","permissions":["INTERNET","ACCESS_NETWORK_STATE","CAMERA","VIBRATE","ACCESS_FINE_LOCATION","ACCESS_COARSE_LOCATION","CALL_PHONE"],"configuration":"Debug","orientations":["portrait","landscapeLeft","landscapeRight","portraitUpsideDown"]}